Workbook

Sheet Sheet1
A1: order_id | B1: region | C1: category | D1: sales | E1: discount | F1: quantity | G1: order_date | H1: delivery_date | I1: customer_type | J1: payment_mode | K1: profit | L1: city
A2: ORD100000 | B2: East | C2: Clothing | D2: 713.49 | E2: 0.31 | F2: 3 | G2: 45015 | H2: 45017 | I2: Member | J2: UPI | K2: 114.72 | L2: Pune
A3: ORD100001 | B3: West | C3: Electronics | D3: 3802.97 | E3: 0.38 | F3: 4 | G3: 45166 | H3: 45172 | I3: Regular | J3: Card | K3: 971.41 | L3: Hyderabad
A4: ORD100002 | B4: North | C4: Home Care | D4: 3588.97 | E4: 0.1 | F4: 7 | G4: 45360 | H4: 45366 | I4: Regular | J4: Cash | K4: 769.08 | L4: Bangalore
A5: ORD100003 | B5: East | C5: Electronics | D5: 1160.86 | E5: 0.27 | F5: 5 | G5: 45578 | H5: 45584 | I5: Member | J5: UPI | K5: 71.61 | L5: Pune
A6: ORD100004 | B6: East | C6: Electronics | D6: 3071.32 | E6: 0 | F6: 7 | G6: 45022 | H6: 45025 | I6: New | J6: Cash | K6: 621.92 | L6: Bangalore
A7: ORD100005 | B7: West | C7: Grocery | D7: 2566.18 | E7: 0.02 | F7: 6 | G7: 45108 | H7: 45111 | I7: Member | J7: UPI | K7: 578.94 | L7: Mumbai
A8: ORD100006 | B8: North | C8: Personal Care | D8: 398 | E8: 0.16 | F8: 4 | G8: 45119 | H8: 45124 | I8: New | J8: Cash | K8: 110.31 | L8: Mumbai
A9: ORD100007 | B9: North | C9: Personal Care | D9: 1462.95 | E9: 0.23 | F9: 2 | G9: 45064 | H9: 45066 | I9: Regular | J9: UPI | K9: 91.68 | L9: Bangalore
A10: ORD100008 | B10: East | C10: Personal Care | D10: 4997.47 | E10: 0.29 | F10: 6 | G10: 45296 | H10: 45299 | I10: Regular | J10: Card | K10: 995.78 | L10: Delhi
A11: ORD100009 | B11: South | C11: Grocery | D11: 587.72 | E11: 0.44 | F11: 6 | G11: 45514 | H11: 45521 | I11: New | J11: Cash | K11: 102.96 | L11: Pune
A12: ORD100010 | B12: East | C12: Clothing | D12: 2581.42 | E12: 0.39 | F12: 6 | G12: 45419 | H12: 45420 | I12: Regular | J12: Cash | K12: 542.82 | L12: Bangalore
A13: ORD100011 | B13: East | C13: Clothing | D13: 4261.74 | E13: 0.15 | F13: 1 | G13: 45171 | H13: 45172 | I13: New | J13: UPI | K13: 1028.47 | L13: Pune
... A15346: ORD115344 | B15346: South | C15346: Grocery | D15346: 4984.32 | E15346: 0.21 | F15346: 3 | G15346: 45248 | H15346: 45249 | I15346: New | J15346: Card | K15346: 909.1 | L15346: Bangalore

Sheet Sheet2
A1: order_id | B1: TASK 1
A2: ORD100000 | B2: =VLOOKUP(A2,Sheet1!A:L,4,FALSE) -> 713.49
A3: ORD100001 | B3: =VLOOKUP(A3,Sheet1!A:L,4,FALSE) -> 3802.97
A4: ORD100002 | B4: =VLOOKUP(A4,Sheet1!A:L,4,FALSE) -> 3588.97
A5: ORD100003 | B5: =VLOOKUP(A5,Sheet1!A:L,4,FALSE) -> 1160.86
A6: ORD100004 | B6: =VLOOKUP(A6,Sheet1!A:L,4,FALSE) -> 3071.32
A7: ORD100005 | B7: =VLOOKUP(A7,Sheet1!A:L,4,FALSE) -> 2566.18
A8: ORD100006 | B8: =VLOOKUP(A8,Sheet1!A:L,4,FALSE) -> 398
A9: ORD100007 | B9: =VLOOKUP(A9,Sheet1!A:L,4,FALSE) -> 1462.95
A10: ORD100008 | B10: =VLOOKUP(A10,Sheet1!A:L,4,FALSE) -> 4997.47
A11: ORD100009 | B11: =VLOOKUP(A11,Sheet1!A:L,4,FALSE) -> 587.72
A12: ORD100010 | B12: =VLOOKUP(A12,Sheet1!A:L,4,FALSE) -> 2581.42
A13: ORD100011 | B13: =VLOOKUP(A13,Sheet1!A:L,4,FALSE) -> 4261.74
... A15346: ORD115344 | B15346: =VLOOKUP(A15346,Sheet1!A:L,4,FALSE) -> 4984.32

Sheet Sheet3
A1: order_id | B1: TASK 2
A2: ORD100000 | B2: =_xlfn.XLOOKUP(A2,Sheet1!A:A,Sheet1!K:K,"NOT FOUND",0) -> 114.72
A3: ORD100001 | B3: =_xlfn.XLOOKUP(A3,Sheet1!A:A,Sheet1!K:K,"NOT FOUND",0) -> 971.41
A4: ORD100002 | B4: =_xlfn.XLOOKUP(A4,Sheet1!A:A,Sheet1!K:K,"NOT FOUND",0) -> 769.08
A5: ORD100003 | B5: =_xlfn.XLOOKUP(A5,Sheet1!A:A,Sheet1!K:K,"NOT FOUND",0) -> 71.61
A6: ORD100004 | B6: =_xlfn.XLOOKUP(A6,Sheet1!A:A,Sheet1!K:K,"NOT FOUND",0) -> 621.92
A7: ORD100005 | B7: =_xlfn.XLOOKUP(A7,Sheet1!A:A,Sheet1!K:K,"NOT FOUND",0) -> 578.94
A8: ORD100006 | B8: =_xlfn.XLOOKUP(A8,Sheet1!A:A,Sheet1!K:K,"NOT FOUND",0) -> 110.31
A9: ORD100007 | B9: =_xlfn.XLOOKUP(A9,Sheet1!A:A,Sheet1!K:K,"NOT FOUND",0) -> 91.68
A10: ORD100008 | B10: =_xlfn.XLOOKUP(A10,Sheet1!A:A,Sheet1!K:K,"NOT FOUND",0) -> 995.78
A11: ORD100009 | B11: =_xlfn.XLOOKUP(A11,Sheet1!A:A,Sheet1!K:K,"NOT FOUND",0) -> 102.96
A12: ORD100010 | B12: =_xlfn.XLOOKUP(A12,Sheet1!A:A,Sheet1!K:K,"NOT FOUND",0) -> 542.82
A13: ORD100011 | B13: =_xlfn.XLOOKUP(A13,Sheet1!A:A,Sheet1!K:K,"NOT FOUND",0) -> 1028.47
... A15346: ORD115344 | B15346: =_xlfn.XLOOKUP(A15346,Sheet1!A:A,Sheet1!K:K,"NOT FOUND",0) -> 909.1

Sheet Sheet4
A1: order_id | B1: TASK 3
A2: ORD100000 | B2: {=INDEX(Sheet1!L:L,MATCH(A2,Sheet1!A:A,0))} -> Pune
A3: ORD100001 | B3: {=INDEX(Sheet1!L:L,MATCH(A3,Sheet1!A:A,0))} -> Hyderabad
A4: ORD100002 | B4: {=INDEX(Sheet1!L:L,MATCH(A4,Sheet1!A:A,0))} -> Bangalore
A5: ORD100003 | B5: {=INDEX(Sheet1!L:L,MATCH(A5,Sheet1!A:A,0))} -> Pune
A6: ORD100004 | B6: {=INDEX(Sheet1!L:L,MATCH(A6,Sheet1!A:A,0))} -> Bangalore
A7: ORD100005 | B7: {=INDEX(Sheet1!L:L,MATCH(A7,Sheet1!A:A,0))} -> Mumbai
A8: ORD100006 | B8: {=INDEX(Sheet1!L:L,MATCH(A8,Sheet1!A:A,0))} -> Mumbai
A9: ORD100007 | B9: {=INDEX(Sheet1!L:L,MATCH(A9,Sheet1!A:A,0))} -> Bangalore
A10: ORD100008 | B10: {=INDEX(Sheet1!L:L,MATCH(A10,Sheet1!A:A,0))} -> Delhi
A11: ORD100009 | B11: {=INDEX(Sheet1!L:L,MATCH(A11,Sheet1!A:A,0))} -> Pune
A12: ORD100010 | B12: {=INDEX(Sheet1!L:L,MATCH(A12,Sheet1!A:A,0))} -> Bangalore
A13: ORD100011 | B13: {=INDEX(Sheet1!L:L,MATCH(A13,Sheet1!A:A,0))} -> Pune
... A15346: ORD115344 | B15346: {=INDEX(Sheet1!L:L,MATCH(A15346,Sheet1!A:A,0))} -> Bangalore
